Metadata-Version: 2.1
Name: mcpybox
Version: 0.0.0
Summary: Minecraft python code tools
Home-page: UNKNOWN
Author: Prisemut (Tristan H.)
Author-email: <tristan.helas@protonmail.com>
License: UNKNOWN
Keywords: python,minecraft,bedrock
Platform: UNKNOWN
Classifier: Development Status :: 1 - Planning
Classifier: Intended Audience :: Developers
Classifier: Programming Language :: Python :: 3
Classifier: Operating System :: Unix
Classifier: Operating System :: MacOS :: MacOS X
Classifier: Operating System :: Microsoft :: Windows
License-File: LICENSE
